edx_event_routing_backends-9.3.6.dist-info/licenses/LICENSE.txt
event_routing_backends/__init__.py
event_routing_backends/admin.py
event_routing_backends/apps.py
event_routing_backends/helpers.py
event_routing_backends/models.py
event_routing_backends/tasks.py
event_routing_backends/backends/__init__.py
event_routing_backends/backends/async_events_router.py
event_routing_backends/backends/events_router.py
event_routing_backends/backends/sync_events_router.py
event_routing_backends/backends/tests/__init__.py
event_routing_backends/backends/tests/test_events_router.py
event_routing_backends/management/__init__.py
event_routing_backends/management/commands/__init__.py
event_routing_backends/management/commands/recover_failed_events.py
event_routing_backends/management/commands/transform_tracking_logs.py
event_routing_backends/management/commands/helpers/__init__.py
event_routing_backends/management/commands/helpers/event_log_parser.py
event_routing_backends/management/commands/helpers/queued_sender.py
event_routing_backends/management/commands/tests/test_recover_failed_events.py
event_routing_backends/management/commands/tests/test_transform_tracking_logs.py
event_routing_backends/migrations/0001_initial.py
event_routing_backends/migrations/0002_auto_20210503_0648.py
event_routing_backends/migrations/0003_auto_20210713_0344.py
event_routing_backends/migrations/0004_auto_20211025_1053.py
event_routing_backends/migrations/__init__.py
event_routing_backends/processors/__init__.py
event_routing_backends/processors/caliper/__init__.py
event_routing_backends/processors/caliper/constants.py
event_routing_backends/processors/caliper/envelope_processor.py
event_routing_backends/processors/caliper/registry.py
event_routing_backends/processors/caliper/transformer.py
event_routing_backends/processors/caliper/transformer_processor.py
event_routing_backends/processors/caliper/event_transformers/__init__.py
event_routing_backends/processors/caliper/event_transformers/enrollment_events.py
edx_event_routing_backends-9.3.6.dist-info/METADATA
edx_event_routing_backends-9.3.6.dist-info/WHEEL
edx_event_routing_backends-9.3.6.dist-info/entry_points.txt
edx_event_routing_backends-9.3.6.dist-info/top_level.txt
edx_event_routing_backends-9.3.6.dist-info/RECORD
