Metadata-Version: 2.4
Name: edx-event-routing-backends
Version: 9.3.6
Summary: Various backends for receiving edX LMS events.
Home-page: https://github.com/openedx/event-routing-backends
Author: edX
Author-email: oscm@edx.org
License: AGPL 3.0
Keywords: Python edx
Classifier: Development Status :: 3 - Alpha
Classifier: Framework :: Django
Classifier: Framework :: Django :: 4.2
Classifier: Framework :: Django :: 5.2
Classifier: Intended Audience :: Developers
Classifier: License :: OSI Approved :: GNU Affero General Public License v3 or later (AGPLv3+)
Classifier: Natural Language :: English
Classifier: Programming Language :: Python :: 3
Classifier: Programming Language :: Python :: 3.11
Classifier: Programming Language :: Python :: 3.12
Requires-Python: >=3.11
License-File: LICENSE.txt
Requires-Dist: Django
Requires-Dist: apache-libcloud
Requires-Dist: django-config-models
Requires-Dist: django-fernet-fields-v2
Requires-Dist: django-redis
Requires-Dist: edx-celeryutils
Requires-Dist: edx-toggles
Requires-Dist: event-tracking
Requires-Dist: fasteners
Requires-Dist: isodate
Requires-Dist: jsonfield
Requires-Dist: openedx-filters
Requires-Dist: python-dateutil
Requires-Dist: pytz
Requires-Dist: requests
Requires-Dist: setuptools
Requires-Dist: tincan
Dynamic: author
Dynamic: author-email
Dynamic: classifier
Dynamic: description
Dynamic: description-content-type
Dynamic: home-page
Dynamic: keywords
Dynamic: license
Dynamic: license-file
Dynamic: requires-dist
Dynamic: requires-python
Dynamic: summary
